ukbsearch/__init__.py
ukbsearch/_logging.py
ukbsearch/_options.py
ukbsearch/block.py
ukbsearch/conf.py
ukbsearch/data.py
ukbsearch/main.py
ukbsearch/tcf.py
ukbsearch/util.py
ukbsearch-0.2.2.dist-info/LICENSE
ukbsearch-0.2.2.dist-info/METADATA
ukbsearch-0.2.2.dist-info/WHEEL
ukbsearch-0.2.2.dist-info/entry_points.txt
ukbsearch-0.2.2.dist-info/top_level.txt
ukbsearch-0.2.2.dist-info/RECORD
