Metadata-Version: 2.1
Name: ukbsearch
Version: 0.2.2
Summary: UNKNOWN
Home-page: https://github.com/danielmsk/ukbsearch
Author: Daniel Minseok Kwon
Author-email: daniel.minseok.kwon@gmail.com
License: MIT
Keywords: genomics,bioinformatics
Platform: UNKNOWN
Classifier: Operating System :: OS Independent
Classifier: Topic :: Software Development :: Libraries
Classifier: License :: OSI Approved :: MIT License
Classifier: Programming Language :: Python :: 3.4
Classifier: Programming Language :: Python :: 3.5
Classifier: Programming Language :: Python :: 3.6
Requires-Dist: rich
Requires-Dist: pyreadr
Requires-Dist: prettytable
Requires-Dist: pandas
Requires-Dist: numpy
Requires-Dist: pytabix
